askchat/__init__.py
askchat/ask.py
askchat/askenv.py
askchat/cli.py
askchat/elements.py
askchat/utils.py
askchat-2.0.0.dist-info/LICENSE
askchat-2.0.0.dist-info/METADATA
askchat-2.0.0.dist-info/WHEEL
askchat-2.0.0.dist-info/entry_points.txt
askchat-2.0.0.dist-info/top_level.txt
askchat-2.0.0.dist-info/RECORD
