Metadata-Version: 2.1
Name: askchat
Version: 2.0.0
Summary: Interact with ChatGPT in terminal via chattool
Author-email: Rex Wang <1073853456@qq.com>
License: MIT
Project-URL: Homepage, https://github.com/cubenlp/askchat
Project-URL: Repository, https://github.com/cubenlp/askchat
Keywords: askchat
Classifier: Development Status :: 2 - Pre-Alpha
Classifier: Intended Audience :: Developers
Classifier: License :: OSI Approved :: MIT License
Classifier: Natural Language :: English
Classifier: Programming Language :: Python :: 3
Classifier: Programming Language :: Python :: 3.6
Classifier: Programming Language :: Python :: 3.7
Classifier: Programming Language :: Python :: 3.8
Classifier: Programming Language :: Python :: 3.9
Requires-Python: >=3.6
License-File: LICENSE
Requires-Dist: chattool>=4.0.0
Requires-Dist: python-dotenv>=0.17.0
Requires-Dist: Click>=8.0
Requires-Dist: platformdirs>=2.0.0
Provides-Extra: dev
Requires-Dist: pip>=25.0; extra == "dev"
Requires-Dist: bump2version; extra == "dev"
Requires-Dist: wheel; extra == "dev"
Requires-Dist: watchdog; extra == "dev"
Requires-Dist: flake8; extra == "dev"
Requires-Dist: tox; extra == "dev"
Requires-Dist: coverage; extra == "dev"
Requires-Dist: Sphinx; extra == "dev"
Requires-Dist: twine; extra == "dev"
Requires-Dist: pytest; extra == "dev"
Requires-Dist: build; extra == "dev"
